chess_mcp/__init__.py
chess_mcp/main.py
chess_mcp/server.py
mseep_chess_mcp-0.1.4.dist-info/licenses/LICENSE
mseep_chess_mcp-0.1.4.dist-info/METADATA
mseep_chess_mcp-0.1.4.dist-info/WHEEL
mseep_chess_mcp-0.1.4.dist-info/entry_points.txt
mseep_chess_mcp-0.1.4.dist-info/top_level.txt
mseep_chess_mcp-0.1.4.dist-info/RECORD
